[{"sqft":36715,"year":null,"units":13,"navLat":33.13868326469525,"navLon":-117.0493049207761,"heading":200.06,"leadUrl":"https://airtable.com/appMPJF8EIQfpWaWO/tblc9yHaPV9IZQN6f/viwt0aEfyiI2pFbKO/recMB4eQy32bhFoRt","latitude":33.1383925,"leadName":["Escondido - E Valley Parkway"],"photoUrl":"https://raw.githubusercontent.com/leadsyfter/images/main/2109-E-Valley-Pkwy_1756831519937","assetType":"Lead / Deal","buildings":1,"longitude":-117.0491813,"addressUrl":"https://www.google.com/maps/search/?api=1&query=2109%20E%20Valley%20Parkway%2C%20Escondido%2C%20CA","propertyName":"E Valley Parkway","assetCategory":"Small-Bay Ind.","propertyAddress":"2109 - 2127 E. Valley Parkway, Escondido, CA"}]