[{"sqft":39068,"year":"1980","units":24,"navLat":37.38324703573759,"navLon":-121.9579946499083,"heading":333.3,"leadUrl":"https://airtable.com/appMPJF8EIQfpWaWO/tblc9yHaPV9IZQN6f/viwt0aEfyiI2pFbKO/recfpN2GvogFmLCrt","latitude":37.3834014,"leadName":"Santa Clara - Thomas Road","photoUrl":"https://raw.githubusercontent.com/leadsyfter/images/main/3501-Thomas-Rd_1757952555298","assetType":"Lead / Deal","buildings":2,"longitude":-121.9580738,"addressUrl":"https://www.google.com/maps/search/?api=1&query=3501%20Thomas%20Road%2C%20Santa%20Clara%2C%20CA","propertyName":"Thomas Road Business Park","assetCategory":"Small-Bay","propertyAddress":"3501-3511 Thomas Road, Santa Clara, CA"}]